termpair/Terminal.py
termpair/__init__.py
termpair/constants.py
termpair/encryption.py
termpair/main.py
termpair/server.py
termpair/server_websocket_subprotocol_handlers.py
termpair/share.py
termpair/utils.py
termpair/frontend_build/asset-manifest.json
termpair/frontend_build/favicon.ico
termpair/frontend_build/index.html
termpair/frontend_build/manifest.json
termpair/frontend_build/static/css/2.cc97c266.chunk.css
termpair/frontend_build/static/css/2.cc97c266.chunk.css.map
termpair/frontend_build/static/css/main.9dd5bed2.chunk.css
termpair/frontend_build/static/css/main.9dd5bed2.chunk.css.map
termpair/frontend_build/static/js/2.7cc8a944.chunk.js
termpair/frontend_build/static/js/2.7cc8a944.chunk.js.LICENSE.txt
termpair/frontend_build/static/js/2.7cc8a944.chunk.js.map
termpair/frontend_build/static/js/main.87de5a0e.chunk.js
termpair/frontend_build/static/js/main.87de5a0e.chunk.js.map
termpair/frontend_build/static/js/runtime-main.546cc18f.js
termpair/frontend_build/static/js/runtime-main.546cc18f.js.map
termpair/frontend_build/static/media/logo.0cb35f08.png
termpair-0.3.1.5.dist-info/LICENSE
termpair-0.3.1.5.dist-info/METADATA
termpair-0.3.1.5.dist-info/WHEEL
termpair-0.3.1.5.dist-info/entry_points.txt
termpair-0.3.1.5.dist-info/top_level.txt
termpair-0.3.1.5.dist-info/RECORD
