Metadata-Version: 2.1
Name: termpair
Version: 0.3.1.5
Summary: View and control remote terminals from your browser with end-to-end encryption
Home-page: https://github.com/cs01/termpair
Author: Chad Smith
Author-email: chadsmith.software@gmail.com
License: License :: OSI Approved :: MIT License
Keywords: e2ee,secure,terminal,share,broadcast,pty,websockets
Classifier: Programming Language :: Python :: 3
Classifier: Operating System :: MacOS
Classifier: Operating System :: POSIX :: Linux
Classifier: Development Status :: 4 - Beta
Requires-Python: >=3.8
License-File: LICENSE
Requires-Dist: aiofiles (==0.8.0)
Requires-Dist: anyio (==3.6.1)
Requires-Dist: asgiref (==3.5.2)
Requires-Dist: cffi (==1.15.0)
Requires-Dist: click (==8.1.3)
Requires-Dist: cryptography (==37.0.3)
Requires-Dist: fastapi (==0.78.0)
Requires-Dist: h11 (==0.13.0)
Requires-Dist: httptools (==0.4.0)
Requires-Dist: idna (==3.3)
Requires-Dist: pycparser (==2.21)
Requires-Dist: pydantic (==1.9.1)
Requires-Dist: python-dotenv (==0.20.0)
Requires-Dist: pyyaml (==6.0)
Requires-Dist: sniffio (==1.2.0)
Requires-Dist: starlette (==0.19.1)
Requires-Dist: typing-extensions (==4.2.0)
Requires-Dist: uvicorn[standard] (==0.17.6)
Requires-Dist: uvloop (==0.16.0)
Requires-Dist: watchgod (==0.8.2)
Requires-Dist: websockets (==10.3)
